{
  "id": "78c26558-17f1-4ee2-a1b5-6a838ce3a677",
  "prevId": "42889d3c-52bb-4ba8-b0b3-758e40c3bec8",
  "version": "5",
  "dialect": "pg",
  "tables": {
    "baseCompanies": {
      "name": "baseCompanies",
      "schema": "",
      "columns": {
        "category": {
          "name": "category",
          "type": "text",
          "primaryKey": false,
          "notNull": false
        },
        "name": {
          "name": "name",
          "type": "text",
          "primaryKey": false,
          "notNull": false
        },
        "type": {
          "name": "type",
          "type": "text",
          "primaryKey": false,
          "notNull": false
        },
        "description": {
          "name": "description",
          "type": "text",
          "primaryKey": false,
          "notNull": false
        },
        "resources": {
          "name": "resources",
          "type": "text",
          "primaryKey": false,
          "notNull": false
        },
        "phonenumber": {
          "name": "phonenumber",
          "type": "text",
          "primaryKey": false,
          "notNull": false
        },
        "email": {
          "name": "email",
          "type": "text",
          "primaryKey": false,
          "notNull": false
        }
      },
      "indexes": {},
      "foreignKeys": {},
      "compositePrimaryKeys": {},
      "uniqueConstraints": {}
    },
    "elaborateCompanies": {
      "name": "elaborateCompanies",
      "schema": "",
      "columns": {
        "category": {
          "name": "category",
          "type": "text",
          "primaryKey": false,
          "notNull": false
        },
        "name": {
          "name": "name",
          "type": "text",
          "primaryKey": false,
          "notNull": false
        },
        "type": {
          "name": "type",
          "type": "text",
          "primaryKey": false,
          "notNull": false
        },
        "description": {
          "name": "description",
          "type": "text",
          "primaryKey": false,
          "notNull": false
        },
        "resources": {
          "name": "resources",
          "type": "text",
          "primaryKey": false,
          "notNull": false
        },
        "phonenumber": {
          "name": "phonenumber",
          "type": "text",
          "primaryKey": false,
          "notNull": false
        },
        "email": {
          "name": "email",
          "type": "text",
          "primaryKey": false,
          "notNull": false
        },
        "genpage": {
          "name": "genpage",
          "type": "jsonb",
          "primaryKey": false,
          "notNull": false
        }
      },
      "indexes": {},
      "foreignKeys": {},
      "compositePrimaryKeys": {},
      "uniqueConstraints": {}
    }
  },
  "enums": {},
  "schemas": {},
  "_meta": {
    "columns": {},
    "schemas": {},
    "tables": {}
  }
}